hearth_cli/__init__.py
hearth_cli/client.py
hearth_cli/config.py
hearth_cli/main.py
hearth_cli/runtime_state.py
hearth_cli/commands/__init__.py
hearth_cli/commands/admin.py
hearth_cli/commands/auth.py
hearth_cli/commands/cache.py
hearth_cli/commands/down.py
hearth_cli/commands/hosts.py
hearth_cli/commands/runs.py
hearth_cli/commands/snapshots.py
hearth_cli/commands/status.py
hearth_cli/commands/up.py
hearth_cli/commands/users.py
hearth_cli/commands/work.py
hearth_common/__init__.py
hearth_common/auth/__init__.py
hearth_common/models/__init__.py
hearth_common/models/task.py
hearth_common/models/worker.py
hearth_common/protocol/__init__.py
hearth_common/protocol/version.py
hearth_common/protocol/ws_messages.py
hearth_common/util/__init__.py
hearth_controller/__init__.py
hearth_controller/config.py
hearth_controller/main.py
hearth_controller/api/__init__.py
hearth_controller/api/artifacts.py
hearth_controller/api/auth.py
hearth_controller/api/deps.py
hearth_controller/api/hosts.py
hearth_controller/api/runs.py
hearth_controller/api/snapshots.py
hearth_controller/api/storage.py
hearth_controller/api/users.py
hearth_controller/db/__init__.py
hearth_controller/db/models.py
hearth_controller/db/session.py
hearth_controller/mcp/__init__.py
hearth_controller/mcp/http_transport.py
hearth_controller/mcp/server.py
hearth_controller/mcp/stdio_server.py
hearth_controller/scripts/__init__.py
hearth_controller/scripts/init_admin.py
hearth_controller/services/__init__.py
hearth_controller/services/auth.py
hearth_controller/services/gc.py
hearth_controller/services/identity.py
hearth_controller/services/reconciler.py
hearth_controller/services/scheduler.py
hearth_controller/services/snapshots.py
hearth_controller/services/storage_coordinator.py
hearth_controller/storage/__init__.py
hearth_controller/storage/client.py
hearth_controller/util/__init__.py
hearth_controller/ws/__init__.py
hearth_controller/ws/client_gateway.py
hearth_controller/ws/gateway.py
hearth_worker/__init__.py
hearthfire-0.1.3.dist-info/METADATA
hearthfire-0.1.3.dist-info/WHEEL
hearthfire-0.1.3.dist-info/entry_points.txt
hearthfire-0.1.3.dist-info/RECORD
