Metadata-Version: 2.4
Name: hearthfire
Version: 0.1.3
Summary: Hearth - Distributed GPU Task Scheduling System
Requires-Python: >=3.10
Requires-Dist: aioboto3>=12.0.0
Requires-Dist: aiosqlite>=0.19.0
Requires-Dist: argon2-cffi>=23.1.0
Requires-Dist: boto3>=1.34.0
Requires-Dist: cryptography>=42.0.0
Requires-Dist: fastapi>=0.110.0
Requires-Dist: filelock>=3.0.0
Requires-Dist: httpx>=0.27.0
Requires-Dist: nvidia-ml-py>=12.0.0
Requires-Dist: psutil>=5.9.0
Requires-Dist: pydantic-settings>=2.0.0
Requires-Dist: pydantic>=2.0.0
Requires-Dist: python-multipart>=0.0.9
Requires-Dist: pyyaml>=6.0.0
Requires-Dist: rich>=13.0.0
Requires-Dist: sqlalchemy[asyncio]>=2.0.0
Requires-Dist: typer>=0.9.0
Requires-Dist: uvicorn>=0.27.0
Requires-Dist: websockets>=12.0
Provides-Extra: dev
Requires-Dist: mypy>=1.8.0; extra == 'dev'
Requires-Dist: pre-commit>=3.6.0; extra == 'dev'
Requires-Dist: pytest-asyncio>=0.23.0; extra == 'dev'
Requires-Dist: pytest-cov>=4.0.0; extra == 'dev'
Requires-Dist: pytest>=8.0.0; extra == 'dev'
Requires-Dist: ruff>=0.4.0; extra == 'dev'
Provides-Extra: mcp
Requires-Dist: mcp>=1.0.0; extra == 'mcp'
